simplicial_kuramoto/__init__.py
simplicial_kuramoto/chimera_measures.py
simplicial_kuramoto/frustration_scan.py
simplicial_kuramoto/graph_generator.py
simplicial_kuramoto/integrators.py
simplicial_kuramoto/measures.py
simplicial_kuramoto/plotting.py
simplicial_kuramoto/simplicial_complex.py
tests/__init__.py
tests/test_xgi.py
simplicial_kuramoto-0.0.2.dist-info/METADATA
simplicial_kuramoto-0.0.2.dist-info/WHEEL
simplicial_kuramoto-0.0.2.dist-info/top_level.txt
simplicial_kuramoto-0.0.2.dist-info/RECORD
